easelog/__init__.py
easelog/easelog.py
tests/__init__.py
tests/easelog_test.py
easelog-0.0.2.dist-info/LICENSE
easelog-0.0.2.dist-info/METADATA
easelog-0.0.2.dist-info/WHEEL
easelog-0.0.2.dist-info/top_level.txt
easelog-0.0.2.dist-info/RECORD
