Metadata-Version: 2.1
Name: easelog
Version: 0.0.2
Summary: A python package for easy log formatting and productivity boost.
Home-page: https://github.com/brworkit/python-package-easelog.git
Author: brworkit
Author-email: brworkit@gmail.com
License: UNKNOWN
Platform: UNKNOWN
Classifier: Programming Language :: Python :: 3
Classifier: License :: OSI Approved :: MIT License
Classifier: Operating System :: OS Independent
Requires-Python: >=3.6
